thapbi_pict/ITS1_DB.sqlite
thapbi_pict/__init__.py
thapbi_pict/__main__.py
thapbi_pict/assess.py
thapbi_pict/classify.py
thapbi_pict/conflicts.py
thapbi_pict/db_import.py
thapbi_pict/db_orm.py
thapbi_pict/denoise.py
thapbi_pict/dump.py
thapbi_pict/edit_graph.py
thapbi_pict/ena_submit.py
thapbi_pict/fasta_nr.py
thapbi_pict/prepare.py
thapbi_pict/sample_tally.py
thapbi_pict/summary.py
thapbi_pict/taxdump.py
thapbi_pict/utils.py
thapbi_pict/versions.py
thapbi_pict-1.0.21.dist-info/licenses/LICENSE.rst
thapbi_pict-1.0.21.dist-info/METADATA
thapbi_pict-1.0.21.dist-info/WHEEL
thapbi_pict-1.0.21.dist-info/entry_points.txt
thapbi_pict-1.0.21.dist-info/top_level.txt
thapbi_pict-1.0.21.dist-info/RECORD
