Metadata-Version: 2.4
Name: thapbi_pict
Version: 1.0.21
Summary: THAPBI Phytophthora ITS1 Classifier Tool (PICT).
Home-page: https://github.com/peterjc/thapbi-pict
Download-URL: https://github.com/peterjc/thapbi-pict
Author: Peter Cock
Author-email: peter.cock@hutton.ac.uk
License: MIT License
Project-URL: Documentation, https://thapbi-pict.readthedocs.io/
Project-URL: Source, https://github.com/peterjc/thapbi-pict/
Project-URL: Tracker, https://github.com/peterjc/thapbi-pict/issues
Classifier: Development Status :: 5 - Production/Stable
Classifier: Environment :: Console
Classifier: Intended Audience :: Science/Research
Classifier: Natural Language :: English
Classifier: Operating System :: MacOS :: MacOS X
Classifier: Operating System :: POSIX :: Linux
Classifier: Programming Language :: Python
Classifier: Programming Language :: Python :: 3
Classifier: Topic :: Scientific/Engineering
Classifier: Topic :: Scientific/Engineering :: Bio-Informatics
Classifier: Topic :: Software Development :: Libraries :: Python Modules
Requires-Python: >=3.10
License-File: LICENSE.rst
Requires-Dist: biopython>=1.84
Requires-Dist: cutadapt>=4.9
Requires-Dist: xopen>=2.0.2
Requires-Dist: matplotlib>=3.9.2
Requires-Dist: networkx>=3.4.2
Requires-Dist: pydot>=3.0.1
Requires-Dist: rapidfuzz>=3.10.1
Requires-Dist: sqlalchemy>=2.0.36
Requires-Dist: xlsxwriter>=3.2.0
Dynamic: author
Dynamic: author-email
Dynamic: classifier
Dynamic: description
Dynamic: description-content-type
Dynamic: download-url
Dynamic: home-page
Dynamic: license
Dynamic: license-file
Dynamic: project-url
Dynamic: requires-dist
Dynamic: requires-python
Dynamic: summary
